GroupyAPI-0.10.3.dist-info/RECORD
GroupyAPI-0.10.3.dist-info/metadata.json
GroupyAPI-0.10.3.dist-info/WHEEL
GroupyAPI-0.10.3.dist-info/DESCRIPTION.rst
GroupyAPI-0.10.3.dist-info/top_level.txt
GroupyAPI-0.10.3.dist-info/METADATA
tests/test_utils.py
tests/test_pagers.py
tests/test_session.py
tests/__init__.py
tests/api/test_user.py
tests/api/test_images.py
tests/api/test_chats.py
tests/api/test_blocks.py
tests/api/__init__.py
tests/api/test_bots.py
tests/api/test_memberships.py
tests/api/test_attachments.py
tests/api/test_base.py
tests/api/base.py
tests/api/test_groups.py
tests/api/test_messages.py
groupy/client.py
groupy/session.py
groupy/__init__.py
groupy/utils.py
groupy/pagers.py
groupy/exceptions.py
groupy/api/user.py
groupy/api/bots.py
groupy/api/__init__.py
groupy/api/groups.py
groupy/api/attachments.py
groupy/api/messages.py
groupy/api/chats.py
groupy/api/blocks.py
groupy/api/base.py
groupy/api/memberships.py
