Metadata-Version: 1.1
Name: GroupyAPI
Version: 0.10.3
Summary: The simple yet powerful wrapper for the GroupMe API
Home-page: https://github.com/rhgrant10/Groupy
Author: Robert Grant
Author-email: rhgrant10@gmail.com
License: Apache Software License, Version 2.0
Keywords: api,GroupMe
Platform: UNKNOWN
Classifier: Development Status :: 5 - Production/Stable
Classifier: Operating System :: OS Independent
Classifier: Topic :: Communications :: Chat
Classifier: Intended Audience :: Developers
Classifier: License :: OSI Approved :: GNU General Public License v2 (GPLv2)
Classifier: Natural Language :: English
Classifier: Programming Language :: Python
Classifier: Programming Language :: Python :: 3
Classifier: Programming Language :: Python :: 3.4
Classifier: Programming Language :: Python :: 3.5
Classifier: Programming Language :: Python :: 3.6
